MANIFEST.in
README.md
install.json
jupyterlab-yq-kfidentity.json
pyproject.toml
setup.cfg
setup.py
js/README.md
js/package-lock.json
js/package.json
js/webpack.config.js
js/yarn.lock
js/dist/index.js
js/dist/index.js.LICENSE.txt
js/lib/embed.js
js/lib/example.js
js/lib/extension.js
js/lib/index.js
js/lib/labplugin.js
jupyter-config/jupyter_notebook_config.d/jupyterlab_yq_kfidentity.json
jupyter-config/jupyter_server_config.d/jupyterlab_yq_kfidentity.json
jupyterlab_yq_kfidentity/__init__.py
jupyterlab_yq_kfidentity/_version.py
jupyterlab_yq_kfidentity/integrations.py
jupyterlab_yq_kfidentity.egg-info/PKG-INFO
jupyterlab_yq_kfidentity.egg-info/SOURCES.txt
jupyterlab_yq_kfidentity.egg-info/dependency_links.txt
jupyterlab_yq_kfidentity.egg-info/not-zip-safe
jupyterlab_yq_kfidentity.egg-info/requires.txt
jupyterlab_yq_kfidentity.egg-info/top_level.txt
jupyterlab_yq_kfidentity/labextension/package.json
jupyterlab_yq_kfidentity/labextension/static/261.dd677a9fa54161dfaeab.js
jupyterlab_yq_kfidentity/labextension/static/486.3499ed4c737386b314e5.js
jupyterlab_yq_kfidentity/labextension/static/486.3499ed4c737386b314e5.js.LICENSE.txt
jupyterlab_yq_kfidentity/labextension/static/568.b343385f5669b0281973.js
jupyterlab_yq_kfidentity/labextension/static/remoteEntry.5caa3eb78f9d1a74f810.js
jupyterlab_yq_kfidentity/labextension/static/style.js
jupyterlab_yq_kfidentity/nbextension/extension.js
jupyterlab_yq_kfidentity/nbextension/index.js
jupyterlab_yq_kfidentity/nbextension/index.js.LICENSE.txt