Metadata-Version: 1.1
Name: jupyterlab-yq-kfidentity
Version: 0.1.8
Summary: Reads JWT from Headers.
Home-page: https://github.com/credo/jupyterlab-yq-kfidentity
Author: Bohdan Astapov
Author-email: bohdan.astapov@credo.be
License: UNKNOWN
Keywords: ipython,jupyter,widgets
Platform: UNKNOWN
Classifier: Development Status :: 4 - Beta
Classifier: Framework :: IPython
Classifier: Intended Audience :: Developers
Classifier: Intended Audience :: Science/Research
Classifier: Topic :: Multimedia :: Graphics
Classifier: Programming Language :: Python :: 3.6
Classifier: Programming Language :: Python :: 3.7
Classifier: Programming Language :: Python :: 3.8
Classifier: Programming Language :: Python :: 3.9
